etcd_client_py_test-0.1.4.dist-info/METADATA
etcd_client_py_test-0.1.4.dist-info/WHEEL
etcd_client_py_test-0.1.4.dist-info/license_files/LICENSE
etcd_client/__init__.py
etcd_client/__init__.pyi
etcd_client/py.typed
etcd_client/etcd_client.cpython-311-x86_64-linux-gnu.so
etcd_client_py_test-0.1.4.dist-info/RECORD
