Metadata-Version: 2.1
Name: etcd-client-py-test
Version: 0.1.4
Classifier: Development Status :: 4 - Beta
Classifier: Programming Language :: Python
License-File: LICENSE
Summary: Yet another etcd-client API binding based on the Rust's etcd-client package
Keywords: etcd,binding,rust,etcd-client
Author: Sanghyeon Seo, Joongi Kim
Author-email: seosh@lablup.com, joongi@lablup.com
License: MIT
Requires-Python: >=3.10
Project-URL: homepage, https://github.com/lablup/etcd-client-py
Project-URL: repository, https://github.com/lablup/etcd-client-py
